{
  "updated": "2026-05-30T18:30:16+09:00",
  "window_short": 5,
  "window_long": 20,
  "stocks": {
    "000150": {
      "last_date": "2026.05.29",
      "short": {
        "inst_volume": -49880,
        "frgn_volume": 88844,
        "inst_value_eok": -860.9,
        "frgn_value_eok": 1634.1,
        "days_available": 5
      },
      "long": {
        "inst_volume": -115687,
        "frgn_volume": 115539,
        "inst_value_eok": -1955.5,
        "frgn_value_eok": 2075.7,
        "days_available": 20
      }
    },
    "000660": {
      "last_date": "2026.05.29",
      "short": {
        "inst_volume": 1050234,
        "frgn_volume": -1506859,
        "inst_value_eok": 22327.9,
        "frgn_value_eok": -33868.9,
        "days_available": 5
      },
      "long": {
        "inst_volume": 2569890,
        "frgn_volume": -11267516,
        "inst_value_eok": 47778.8,
        "frgn_value_eok": -212396.1,
        "days_available": 20
      }
    },
    "003230": {
      "last_date": "2026.05.29",
      "short": {
        "inst_volume": -70353,
        "frgn_volume": 27276,
        "inst_value_eok": -893.1,
        "frgn_value_eok": 355.3,
        "days_available": 5
      },
      "long": {
        "inst_volume": 8948,
        "frgn_volume": 17755,
        "inst_value_eok": 252.2,
        "frgn_value_eok": 262.2,
        "days_available": 20
      }
    },
    "005930": {
      "last_date": "2026.05.29",
      "short": {
        "inst_volume": 6457484,
        "frgn_volume": -8037000,
        "inst_value_eok": 20400.5,
        "frgn_value_eok": -24047.3,
        "days_available": 5
      },
      "long": {
        "inst_volume": 22999299,
        "frgn_volume": -55138975,
        "inst_value_eok": 64820.7,
        "frgn_value_eok": -156988.8,
        "days_available": 20
      }
    },
    "007660": {
      "last_date": "2026.05.29",
      "short": {
        "inst_volume": 650348,
        "frgn_volume": -1105129,
        "inst_value_eok": 861.3,
        "frgn_value_eok": -1430.9,
        "days_available": 5
      },
      "long": {
        "inst_volume": 329780,
        "frgn_volume": -2977398,
        "inst_value_eok": 432.7,
        "frgn_value_eok": -3898.8,
        "days_available": 20
      }
    },
    "020000": {
      "last_date": "2026.05.29",
      "short": {
        "inst_volume": -105451,
        "frgn_volume": 205070,
        "inst_value_eok": -24.4,
        "frgn_value_eok": 47.6,
        "days_available": 5
      },
      "long": {
        "inst_volume": 394581,
        "frgn_volume": 30571,
        "inst_value_eok": 106.8,
        "frgn_value_eok": 0.9,
        "days_available": 20
      }
    },
    "032830": {
      "last_date": "2026.05.29",
      "short": {
        "inst_volume": 30592,
        "frgn_volume": -28126,
        "inst_value_eok": 133.2,
        "frgn_value_eok": -114.8,
        "days_available": 5
      },
      "long": {
        "inst_volume": 735906,
        "frgn_volume": -509569,
        "inst_value_eok": 2363.5,
        "frgn_value_eok": -1673.2,
        "days_available": 20
      }
    },
    "034020": {
      "last_date": "2026.05.29",
      "short": {
        "inst_volume": -526077,
        "frgn_volume": -774645,
        "inst_value_eok": -580.0,
        "frgn_value_eok": -854.0,
        "days_available": 5
      },
      "long": {
        "inst_volume": -3210657,
        "frgn_volume": -3861196,
        "inst_value_eok": -3795.0,
        "frgn_value_eok": -4441.9,
        "days_available": 20
      }
    },
    "042660": {
      "last_date": "2026.05.29",
      "short": {
        "inst_volume": 36570,
        "frgn_volume": 1029280,
        "inst_value_eok": 59.9,
        "frgn_value_eok": 1416.4,
        "days_available": 5
      },
      "long": {
        "inst_volume": -150,
        "frgn_volume": 99378,
        "inst_value_eok": -47.1,
        "frgn_value_eok": 438.2,
        "days_available": 20
      }
    },
    "082740": {
      "last_date": "2026.05.29",
      "short": {
        "inst_volume": -467046,
        "frgn_volume": -10588,
        "inst_value_eok": -307.5,
        "frgn_value_eok": -46.1,
        "days_available": 5
      },
      "long": {
        "inst_volume": -711180,
        "frgn_volume": 572821,
        "inst_value_eok": -507.2,
        "frgn_value_eok": 493.1,
        "days_available": 20
      }
    },
    "171090": {
      "last_date": "2026.05.29",
      "short": {
        "inst_volume": 89202,
        "frgn_volume": -22438,
        "inst_value_eok": 84.0,
        "frgn_value_eok": -19.3,
        "days_available": 5
      },
      "long": {
        "inst_volume": -163642,
        "frgn_volume": -105343,
        "inst_value_eok": -153.3,
        "frgn_value_eok": -99.9,
        "days_available": 20
      }
    },
    "267270": {
      "last_date": "2026.05.29",
      "short": {
        "inst_volume": -347115,
        "frgn_volume": -11996,
        "inst_value_eok": -535.5,
        "frgn_value_eok": -41.1,
        "days_available": 5
      },
      "long": {
        "inst_volume": -1066223,
        "frgn_volume": 501308,
        "inst_value_eok": -1784.1,
        "frgn_value_eok": 859.9,
        "days_available": 20
      }
    },
    "295310": {
      "last_date": "2026.05.29",
      "short": {
        "inst_volume": -60492,
        "frgn_volume": 146683,
        "inst_value_eok": -74.0,
        "frgn_value_eok": 191.2,
        "days_available": 5
      },
      "long": {
        "inst_volume": 53218,
        "frgn_volume": 327881,
        "inst_value_eok": 79.3,
        "frgn_value_eok": 368.8,
        "days_available": 20
      }
    },
    "307950": {
      "last_date": "2026.05.29",
      "short": {
        "inst_volume": 91373,
        "frgn_volume": 4449,
        "inst_value_eok": 715.8,
        "frgn_value_eok": 6.4,
        "days_available": 5
      },
      "long": {
        "inst_volume": 228390,
        "frgn_volume": -64246,
        "inst_value_eok": 1640.8,
        "frgn_value_eok": -316.2,
        "days_available": 20
      }
    },
    "402340": {
      "last_date": "2026.05.29",
      "short": {
        "inst_volume": 242945,
        "frgn_volume": -41822,
        "inst_value_eok": 2998.3,
        "frgn_value_eok": -477.7,
        "days_available": 5
      },
      "long": {
        "inst_volume": 1094308,
        "frgn_volume": -1408649,
        "inst_value_eok": 12595.0,
        "frgn_value_eok": -15235.6,
        "days_available": 20
      }
    }
  },
  "failed_codes": []
}