{
  "삼성 트루밸류 / NH Value ESG / DB 개방형": [
    {
      "code": "005930",
      "name": "삼성전자",
      "sector": "반도체",
      "market_cap": 18708091.5456,
      "weight": 30,
      "weight_prev": 30.0,
      "today_return": 5.936454849498328,
      "contribution": 17.809364548494983,
      "cumulative_return": 432.05490101091266,
      "current_price": 316750.0,
      "ath_price": 316750.0,
      "dd": 0.0,
      "rsi_1m": 12.119214031180404,
      "is_today_new": false
    },
    {
      "code": "000660",
      "name": "SK하이닉스",
      "sector": "반도체",
      "market_cap": 15900389.76315,
      "weight": 22,
      "weight_prev": 22.0,
      "today_return": 9.600389863547758,
      "contribution": 21.120857699805068,
      "cumulative_return": 667.3952622333604,
      "current_price": 2249000.0,
      "ath_price": 2249000.0,
      "dd": 0.0,
      "rsi_1m": 54.61973673469388,
      "is_today_new": false
    },
    {
      "code": "000150",
      "name": "두산",
      "sector": "상사,자본재",
      "market_cap": 287278.6329,
      "weight": 5,
      "weight_prev": 5.0,
      "today_return": -2.18978102189781,
      "contribution": -1.094890510948905,
      "cumulative_return": 80.82425424994608,
      "current_price": 1742000.0,
      "ath_price": 1817000.0,
      "dd": -4.127682993946069,
      "rsi_1m": -8.167661719833575,
      "is_today_new": false
    },
    {
      "code": "295310",
      "name": "에이치브이엠",
      "sector": "비철,목재등",
      "market_cap": 15479.123517,
      "weight": 5,
      "weight_prev": 5.0,
      "today_return": -4.06015037593985,
      "contribution": -2.030075187969925,
      "cumulative_return": 14.336917562724016,
      "current_price": 127600.0,
      "ath_price": 133000.0,
      "dd": -4.060150375939853,
      "rsi_1m": 47.56696018202503,
      "is_today_new": false
    },
    {
      "code": "032830",
      "name": "삼성생명",
      "sector": "보험",
      "market_cap": 730000.0,
      "weight": 5,
      "weight_prev": 5.0,
      "today_return": 4.310344827586207,
      "contribution": 2.1551724137931036,
      "cumulative_return": 6.94617563739377,
      "current_price": 363000.0,
      "ath_price": 364500.0,
      "dd": -0.4115226337448541,
      "rsi_1m": 13.102263992172213,
      "is_today_new": false
    },
    {
      "code": "034020",
      "name": "두산에너빌리티",
      "sector": "기계",
      "market_cap": 727036.90071,
      "weight": 3,
      "weight_prev": 3.0,
      "today_return": -1.1545293072824157,
      "contribution": -0.34635879218472465,
      "cumulative_return": 65.49319648993837,
      "current_price": 111300.0,
      "ath_price": 136400.0,
      "dd": -18.401759530791782,
      "rsi_1m": -38.18906574225123,
      "is_today_new": false
    },
    {
      "code": "042660",
      "name": "한화오션",
      "sector": "조선",
      "market_cap": 412738.841718,
      "weight": 3,
      "weight_prev": 3.0,
      "today_return": -2.1529324424647367,
      "contribution": -0.645879732739421,
      "cumulative_return": 2.5565079883030695,
      "current_price": 131800.0,
      "ath_price": 151475.0,
      "dd": -12.988942069648457,
      "rsi_1m": -30.906623809523815,
      "is_today_new": false
    },
    {
      "code": "007660",
      "name": "이수페타시스",
      "sector": "IT하드웨어",
      "market_cap": 107838.142711,
      "weight": 3,
      "weight_prev": 3.0,
      "today_return": -2.576950608446672,
      "contribution": -0.7730851825340015,
      "cumulative_return": -3.7754524886877805,
      "current_price": 136100.0,
      "ath_price": 161400.0,
      "dd": -15.675340768277568,
      "rsi_1m": -38.35958335552596,
      "is_today_new": false
    },
    {
      "code": "006800",
      "name": "미래에셋증권",
      "sector": "증권",
      "market_cap": 378267.21088,
      "weight": 3,
      "weight_prev": 3.0,
      "today_return": -1.7937219730941705,
      "contribution": -0.538116591928251,
      "cumulative_return": 208.92061163459914,
      "current_price": 65700.0,
      "ath_price": 83800.0,
      "dd": -21.599045346062052,
      "rsi_1m": -31.926309748892166,
      "is_today_new": false
    },
    {
      "code": "267270",
      "name": "HD건설기계",
      "sector": "기타",
      "market_cap": 80892.162136,
      "weight": 3,
      "weight_prev": 3.0,
      "today_return": 2.370820668693009,
      "contribution": 0.7112462006079027,
      "cumulative_return": -4.813942534149785,
      "current_price": 168400.0,
      "ath_price": 198100.0,
      "dd": -14.992428066633012,
      "rsi_1m": -38.09244538586076,
      "is_today_new": false
    },
    {
      "code": "171090",
      "name": "선익시스템",
      "sector": "디스플레이",
      "market_cap": 9122.671278,
      "weight": 3,
      "weight_prev": 3.0,
      "today_return": -2.18978102189781,
      "contribution": -0.6569343065693432,
      "cumulative_return": -2.096199008436983,
      "current_price": 93800.0,
      "ath_price": 131000.0,
      "dd": -28.396946564885496,
      "rsi_1m": -8.434501901140683,
      "is_today_new": false
    },
    {
      "code": "020000",
      "name": "한섬",
      "sector": "화장품,의류,완구",
      "market_cap": 4886.016135,
      "weight": 2,
      "weight_prev": 2.0,
      "today_return": -1.0822510822510822,
      "contribution": -0.21645021645021645,
      "cumulative_return": -11.452172139506423,
      "current_price": 22850.0,
      "ath_price": 51000.0,
      "dd": -55.196078431372555,
      "rsi_1m": -38.117229224652085,
      "is_today_new": false
    },
    {
      "code": "082740",
      "name": "한화엔진",
      "sector": "기타",
      "market_cap": 63670.169346,
      "weight": 2,
      "weight_prev": 2.0,
      "today_return": -11.096938775510203,
      "contribution": -2.219387755102041,
      "cumulative_return": -11.079926006251196,
      "current_price": 69700.0,
      "ath_price": 89500.0,
      "dd": -22.12290502793296,
      "rsi_1m": -29.54271340941512,
      "is_today_new": false
    },
    {
      "code": "003230",
      "name": "삼양식품",
      "sector": "필수소비재",
      "market_cap": 96196.60155,
      "weight": 2,
      "weight_prev": 2.0,
      "today_return": -2.7777777777777777,
      "contribution": -0.5555555555555556,
      "cumulative_return": -7.568162367037545,
      "current_price": 1260000.0,
      "ath_price": 1630000.0,
      "dd": -22.699386503067487,
      "rsi_1m": -35.2221,
      "is_today_new": false
    },
    {
      "code": "307950",
      "name": "현대오토에버",
      "sector": "소프트웨어",
      "market_cap": 171399.8875,
      "weight": 2,
      "weight_prev": 2.0,
      "today_return": 0.0,
      "contribution": 0.0,
      "cumulative_return": 0.8429926238145535,
      "current_price": 638000.0,
      "ath_price": 699000.0,
      "dd": -8.72675250357654,
      "rsi_1m": 16.027899999999995,
      "is_today_new": false
    },
    {
      "code": "491000",
      "name": "리브스메드",
      "sector": "기타",
      "market_cap": 16727.937579,
      "weight": 2,
      "weight_prev": 2.0,
      "today_return": -14.150943396226415,
      "contribution": -2.830188679245283,
      "cumulative_return": -11.033519553072624,
      "current_price": 63700.0,
      "ath_price": 91300.0,
      "dd": -30.230010952902518,
      "rsi_1m": 9.281194630872475,
      "is_today_new": false
    },
    {
      "code": "007810",
      "name": "코리아써키트",
      "sector": "IT하드웨어",
      "market_cap": 28539.3178,
      "weight": 2,
      "weight_prev": 2.0,
      "today_return": -3.2667876588021776,
      "contribution": -0.6533575317604355,
      "cumulative_return": -3.2667876588021727,
      "current_price": 106600.0,
      "ath_price": 110200.0,
      "dd": -3.2667876588021727,
      "rsi_1m": -12.086135087719308,
      "is_today_new": false
    }
  ]
}