{
  "삼성 트루밸류 / NH Value ESG / DB 개방형": [
    {
      "code": "005930",
      "name": "삼성전자",
      "sector": "반도체",
      "market_cap": 10898053.0,
      "weight": 30,
      "today_return": -2.0223523150612026,
      "contribution": -6.067056945183608,
      "cumulative_return": 193.9329430548164,
      "is_today_new": false
    },
    {
      "code": "000660",
      "name": "SK하이닉스",
      "sector": "반도체",
      "market_cap": 6556862.0,
      "weight": 15,
      "today_return": -1.0752688172043012,
      "contribution": -1.6129032258064515,
      "cumulative_return": 199.74193548387095,
      "is_today_new": false
    },
    {
      "code": "352820",
      "name": "하이브",
      "sector": "미디어,교육",
      "market_cap": 156121.0,
      "weight": 8,
      "today_return": 1.971830985915493,
      "contribution": 1.5774647887323945,
      "cumulative_return": 73.35211267605632,
      "is_today_new": false
    },
    {
      "code": "001040",
      "name": "CJ",
      "sector": "상사,자본재",
      "market_cap": 52519.0,
      "weight": 8,
      "today_return": -0.16638935108153077,
      "contribution": -0.13311148086522462,
      "cumulative_return": 87.68718801996671,
      "is_today_new": false
    },
    {
      "code": "277810",
      "name": "레인보우로보틱스",
      "sector": "기계",
      "market_cap": 146469.0,
      "weight": 8,
      "today_return": -0.6578947368421052,
      "contribution": -0.5263157894736842,
      "cumulative_return": 10.43712271140016,
      "is_today_new": false
    },
    {
      "code": "034020",
      "name": "두산에너빌리티",
      "sector": "기계",
      "market_cap": 684440.0,
      "weight": 5,
      "today_return": 3.2367149758454103,
      "contribution": 1.6183574879227052,
      "cumulative_return": 46.596135265700475,
      "is_today_new": false
    },
    {
      "code": "000150",
      "name": "두산",
      "sector": "상사,자본재",
      "market_cap": 179833.0,
      "weight": 5,
      "today_return": -2.84339457567804,
      "contribution": -1.42169728783902,
      "cumulative_return": -1.8718285214348152,
      "is_today_new": false
    },
    {
      "code": "006800",
      "name": "미래에셋증권",
      "sector": "증권",
      "market_cap": 396960.0,
      "weight": 3,
      "today_return": -0.5681818181818182,
      "contribution": -0.17045454545454544,
      "cumulative_return": 148.57954545454547,
      "is_today_new": false
    },
    {
      "code": "010060",
      "name": "OCI홀딩스",
      "sector": "화학",
      "market_cap": 30675.0,
      "weight": 3,
      "today_return": -0.9047044632086853,
      "contribution": -0.27141133896260555,
      "cumulative_return": 53.59770808202655,
      "is_today_new": false
    },
    {
      "code": "006400",
      "name": "삼성SDI",
      "sector": "IT가전",
      "market_cap": 317104.0,
      "weight": 3,
      "today_return": -1.625,
      "contribution": -0.4875,
      "cumulative_return": -0.28079324634595615,
      "is_today_new": false
    },
    {
      "code": "241560",
      "name": "두산밥캣",
      "sector": "기계",
      "market_cap": 58376.0,
      "weight": 3,
      "today_return": 0.3294892915980231,
      "contribution": 0.09884678747940692,
      "cumulative_return": -4.268454400966403,
      "is_today_new": false
    },
    {
      "code": "112610",
      "name": "씨에스윈드",
      "sector": "에너지",
      "market_cap": 23447.0,
      "weight": 3,
      "today_return": -0.7142857142857143,
      "contribution": -0.21428571428571427,
      "cumulative_return": 4.649966147596474,
      "is_today_new": false
    },
    {
      "code": "439260",
      "name": "대한조선",
      "sector": "기타",
      "market_cap": 38565.0,
      "weight": 3,
      "today_return": -0.3980099502487562,
      "contribution": -0.11940298507462685,
      "cumulative_return": 0.20260506512661536,
      "is_today_new": false
    }
  ]
}