{
  "삼성 트루밸류 / NH 다이내믹 밸류 / DB 개방형": [
    {
      "code": "005930",
      "name": "삼성전자",
      "sector": "반도체",
      "market_cap": 17246522,
      "weight": 30.0,
      "weight_prev": 30.0,
      "today_return": 6.47,
      "contribution": 19.409999999999997,
      "cumulative_return": 427.5809365946772,
      "current_price": 295000.0,
      "ath_price": 362500.0,
      "dd": -18.620689655172416,
      "rsi": 97.53812758308766,
      "is_today_new": false
    },
    {
      "code": "000660",
      "name": "SK하이닉스",
      "sector": "반도체",
      "market_cap": 16107073,
      "weight": 30.0,
      "weight_prev": 25.0,
      "today_return": 3.43,
      "contribution": 8.575000000000001,
      "cumulative_return": 695.1285994429101,
      "current_price": 2253000.0,
      "ath_price": 2919000.0,
      "dd": -22.816032887975336,
      "rsi": 221.36908701368085,
      "is_today_new": false
    },
    {
      "code": "105560",
      "name": "KB금융",
      "sector": "은행",
      "market_cap": 661847,
      "weight": 5.0,
      "weight_prev": 3.0,
      "today_return": 8.81,
      "contribution": 2.6430000000000002,
      "cumulative_return": 21.718556021569803,
      "current_price": 186700.0,
      "ath_price": 186700.0,
      "dd": 0.0,
      "rsi": 34.60662054329682,
      "is_today_new": false
    },
    {
      "code": "032830",
      "name": "삼성생명",
      "sector": "보험",
      "market_cap": 682000,
      "weight": 3.0,
      "weight_prev": 3.0,
      "today_return": 4.6,
      "contribution": 1.38,
      "cumulative_return": 10.130797773654932,
      "current_price": 340500.0,
      "ath_price": 497000.0,
      "dd": -31.48893360160966,
      "rsi": 11.820642650176527,
      "is_today_new": false
    },
    {
      "code": "298380",
      "name": "에이비엘바이오",
      "sector": "건강관리",
      "market_cap": 46134,
      "weight": 2.0,
      "weight_prev": 2.0,
      "today_return": 2.36,
      "contribution": 0.472,
      "cumulative_return": -17.421329839502132,
      "current_price": 82100.0,
      "ath_price": 245500.0,
      "dd": -66.55804480651732,
      "rsi": -1.1330257992420045,
      "is_today_new": false
    },
    {
      "code": "141080",
      "name": "리가켐바이오",
      "sector": "건강관리",
      "market_cap": 44942,
      "weight": 2.0,
      "weight_prev": 2.0,
      "today_return": 2.71,
      "contribution": 0.5419999999999999,
      "cumulative_return": -16.589669716581124,
      "current_price": 121300.0,
      "ath_price": 213500.0,
      "dd": -43.18501170960187,
      "rsi": -7.830096367483175,
      "is_today_new": false
    },
    {
      "code": "196170",
      "name": "알테오젠",
      "sector": "건강관리",
      "market_cap": 174424,
      "weight": 2.0,
      "weight_prev": 2.0,
      "today_return": 8.5,
      "contribution": 1.7000000000000002,
      "cumulative_return": -2.934192360791543,
      "current_price": 324000.0,
      "ath_price": 559000.0,
      "dd": -42.039355992844364,
      "rsi": -0.10495882336234441,
      "is_today_new": false
    },
    {
      "code": "226950",
      "name": "올릭스",
      "sector": "건강관리",
      "market_cap": 25241,
      "weight": 2.0,
      "weight_prev": 2.0,
      "today_return": 2.31,
      "contribution": 0.462,
      "cumulative_return": -7.413677685950426,
      "current_price": 124100.0,
      "ath_price": 207000.0,
      "dd": -40.048309178743956,
      "rsi": 2.3486739262311707,
      "is_today_new": false
    },
    {
      "code": "003230",
      "name": "삼양식품",
      "sector": "필수소비재",
      "market_cap": 84972,
      "weight": 2.0,
      "weight_prev": 2.0,
      "today_return": 2.27,
      "contribution": 0.454,
      "cumulative_return": -20.188179291174436,
      "current_price": 1123000.0,
      "ath_price": 1630000.0,
      "dd": -31.104294478527606,
      "rsi": -13.320869763747279,
      "is_today_new": false
    },
    {
      "code": "067310",
      "name": "하나마이크론",
      "sector": "반도체",
      "market_cap": 26891,
      "weight": 2.0,
      "weight_prev": 2.0,
      "today_return": 15.06,
      "contribution": 3.0120000000000005,
      "cumulative_return": 7.611028901734107,
      "current_price": 40450.0,
      "ath_price": 56800.0,
      "dd": -28.785211267605636,
      "rsi": 11.485115103744448,
      "is_today_new": false
    },
    {
      "code": "004170",
      "name": "신세계",
      "sector": "소매(유통)",
      "market_cap": 59127,
      "weight": 2.0,
      "weight_prev": 2.0,
      "today_return": 3.47,
      "contribution": 0.6940000000000001,
      "cumulative_return": -14.208980132450344,
      "current_price": 626000.0,
      "ath_price": 776000.0,
      "dd": -19.329896907216494,
      "rsi": -3.111306011316961,
      "is_today_new": false
    },
    {
      "code": "237690",
      "name": "에스티팜",
      "sector": "건강관리",
      "market_cap": 26095,
      "weight": 2.0,
      "weight_prev": 2.0,
      "today_return": 4.78,
      "contribution": 0.9560000000000001,
      "cumulative_return": -0.9266263237518779,
      "current_price": 125000.0,
      "ath_price": 168700.0,
      "dd": -25.90397154712507,
      "rsi": 7.889513879391796,
      "is_today_new": false
    }
  ],
  "NH 목표전환형 5호": [
    {
      "code": "005930",
      "name": "삼성전자",
      "sector": "반도체",
      "market_cap": 17246522,
      "weight": 30.0,
      "weight_prev": 25.0,
      "today_return": 6.47,
      "contribution": 16.174999999999997,
      "cumulative_return": -0.5005807814150054,
      "current_price": 295000.0,
      "ath_price": 362500.0,
      "dd": -18.620689655172416,
      "rsi": 4.467493016108836,
      "is_today_new": false
    },
    {
      "code": "000660",
      "name": "SK하이닉스",
      "sector": "반도체",
      "market_cap": 16107073,
      "weight": 30.0,
      "weight_prev": 25.0,
      "today_return": 3.43,
      "contribution": 8.575000000000001,
      "cumulative_return": -6.714255404323454,
      "current_price": 2253000.0,
      "ath_price": 2919000.0,
      "dd": -22.816032887975336,
      "rsi": -1.1331827264304262,
      "is_today_new": false
    },
    {
      "code": "105560",
      "name": "KB금융",
      "sector": "은행",
      "market_cap": 661847,
      "weight": 7.0,
      "weight_prev": 7.0,
      "today_return": 8.81,
      "contribution": 6.167000000000002,
      "cumulative_return": 30.882456511734937,
      "current_price": 186700.0,
      "ath_price": 186700.0,
      "dd": 0.0,
      "rsi": 34.60662054329682,
      "is_today_new": false
    },
    {
      "code": "196170",
      "name": "알테오젠",
      "sector": "건강관리",
      "market_cap": 174424,
      "weight": 2.0,
      "weight_prev": 2.0,
      "today_return": 8.5,
      "contribution": 1.7000000000000002,
      "cumulative_return": -5.753351206434321,
      "current_price": 324000.0,
      "ath_price": 559000.0,
      "dd": -42.039355992844364,
      "rsi": 0.6123610150501002,
      "is_today_new": false
    },
    {
      "code": "141080",
      "name": "리가켐바이오",
      "sector": "건강관리",
      "market_cap": 44942,
      "weight": 2.0,
      "weight_prev": 2.0,
      "today_return": 2.71,
      "contribution": 0.5419999999999999,
      "cumulative_return": -23.51919582565992,
      "current_price": 121300.0,
      "ath_price": 213500.0,
      "dd": -43.18501170960187,
      "rsi": -11.788049111723842,
      "is_today_new": false
    },
    {
      "code": "237690",
      "name": "에스티팜",
      "sector": "건강관리",
      "market_cap": 26095,
      "weight": 2.0,
      "weight_prev": 2.0,
      "today_return": 4.78,
      "contribution": 0.9560000000000001,
      "cumulative_return": -0.9266263237518779,
      "current_price": 125000.0,
      "ath_price": 168700.0,
      "dd": -25.90397154712507,
      "rsi": 7.889513879391796,
      "is_today_new": false
    },
    {
      "code": "298380",
      "name": "에이비엘바이오",
      "sector": "건강관리",
      "market_cap": 46134,
      "weight": 2.0,
      "weight_prev": 2.0,
      "today_return": 2.36,
      "contribution": 0.472,
      "cumulative_return": -15.54014070351758,
      "current_price": 82100.0,
      "ath_price": 245500.0,
      "dd": -66.55804480651732,
      "rsi": -4.151629811832858,
      "is_today_new": false
    },
    {
      "code": "226950",
      "name": "올릭스",
      "sector": "건강관리",
      "market_cap": 25241,
      "weight": 2.0,
      "weight_prev": 2.0,
      "today_return": 2.31,
      "contribution": 0.462,
      "cumulative_return": -18.401857326478154,
      "current_price": 124100.0,
      "ath_price": 207000.0,
      "dd": -40.048309178743956,
      "rsi": -6.9084085642065585,
      "is_today_new": false
    }
  ],
  "DB 목표전환형 6차": [
    {
      "code": "005930",
      "name": "삼성전자",
      "sector": "반도체",
      "market_cap": 17246522,
      "weight": 30.0,
      "weight_prev": 25.0,
      "today_return": 6.47,
      "contribution": 16.174999999999997,
      "cumulative_return": 1.9209843158463968,
      "current_price": 295000.0,
      "ath_price": 362500.0,
      "dd": -18.620689655172416,
      "rsi": 5.981424234867516,
      "is_today_new": false
    },
    {
      "code": "000660",
      "name": "SK하이닉스",
      "sector": "반도체",
      "market_cap": 16107073,
      "weight": 30.0,
      "weight_prev": 25.0,
      "today_return": 3.43,
      "contribution": 8.575000000000001,
      "cumulative_return": -4.847778685177628,
      "current_price": 2253000.0,
      "ath_price": 2919000.0,
      "dd": -22.816032887975336,
      "rsi": 0.18955469989136997,
      "is_today_new": false
    },
    {
      "code": "105560",
      "name": "KB금융",
      "sector": "은행",
      "market_cap": 661847,
      "weight": 7.0,
      "weight_prev": 7.0,
      "today_return": 8.81,
      "contribution": 6.167000000000002,
      "cumulative_return": 28.169255520504755,
      "current_price": 186700.0,
      "ath_price": 186700.0,
      "dd": 0.0,
      "rsi": 29.973540307146894,
      "is_today_new": false
    },
    {
      "code": "196170",
      "name": "알테오젠",
      "sector": "건강관리",
      "market_cap": 174424,
      "weight": 2.0,
      "weight_prev": 2.0,
      "today_return": 8.5,
      "contribution": 1.7000000000000002,
      "cumulative_return": -1.8044692737430146,
      "current_price": 324000.0,
      "ath_price": 559000.0,
      "dd": -42.039355992844364,
      "rsi": 5.066735836574676,
      "is_today_new": false
    },
    {
      "code": "141080",
      "name": "리가켐바이오",
      "sector": "건강관리",
      "market_cap": 44942,
      "weight": 2.0,
      "weight_prev": 2.0,
      "today_return": 2.71,
      "contribution": 0.5419999999999999,
      "cumulative_return": -16.94184666666668,
      "current_price": 121300.0,
      "ath_price": 213500.0,
      "dd": -43.18501170960187,
      "rsi": -4.569390792848049,
      "is_today_new": false
    },
    {
      "code": "237690",
      "name": "에스티팜",
      "sector": "건강관리",
      "market_cap": 26095,
      "weight": 2.0,
      "weight_prev": 2.0,
      "today_return": 4.78,
      "contribution": 0.9560000000000001,
      "cumulative_return": -0.47492401215805113,
      "current_price": 125000.0,
      "ath_price": 168700.0,
      "dd": -25.90397154712507,
      "rsi": 9.548744972096223,
      "is_today_new": false
    },
    {
      "code": "298380",
      "name": "에이비엘바이오",
      "sector": "건강관리",
      "market_cap": 46134,
      "weight": 2.0,
      "weight_prev": 2.0,
      "today_return": 2.36,
      "contribution": 0.472,
      "cumulative_return": -17.204374384236452,
      "current_price": 82100.0,
      "ath_price": 245500.0,
      "dd": -66.55804480651732,
      "rsi": -4.549357952125554,
      "is_today_new": false
    },
    {
      "code": "226950",
      "name": "올릭스",
      "sector": "건강관리",
      "market_cap": 25241,
      "weight": 2.0,
      "weight_prev": 2.0,
      "today_return": 2.31,
      "contribution": 0.462,
      "cumulative_return": -23.972029940119764,
      "current_price": 124100.0,
      "ath_price": 207000.0,
      "dd": -40.048309178743956,
      "rsi": -11.124680214005734,
      "is_today_new": false
    }
  ],
  "한투 지속형": [
    {
      "code": "005930",
      "name": "삼성전자",
      "sector": "반도체",
      "market_cap": 17246522,
      "weight": 30.0,
      "weight_prev": 20.0,
      "today_return": 6.47,
      "contribution": 12.94,
      "cumulative_return": 8.057282110091734,
      "current_price": 295000.0,
      "ath_price": 362500.0,
      "dd": -18.620689655172416,
      "rsi": 7.803963614956954,
      "is_today_new": false
    },
    {
      "code": "000660",
      "name": "SK하이닉스",
      "sector": "반도체",
      "market_cap": 16107073,
      "weight": 30.0,
      "weight_prev": 20.0,
      "today_return": 3.43,
      "contribution": 6.860000000000001,
      "cumulative_return": 6.267898457095078,
      "current_price": 2253000.0,
      "ath_price": 2919000.0,
      "dd": -22.816032887975336,
      "rsi": 7.67494311556608,
      "is_today_new": false
    },
    {
      "code": "105560",
      "name": "KB금융",
      "sector": "은행",
      "market_cap": 661847,
      "weight": 5.0,
      "weight_prev": 5.0,
      "today_return": 8.81,
      "contribution": 4.405000000000001,
      "cumulative_return": 23.120163636363642,
      "current_price": 186700.0,
      "ath_price": 186700.0,
      "dd": 0.0,
      "rsi": 17.80862561961897,
      "is_today_new": false
    },
    {
      "code": "402340",
      "name": "SK스퀘어",
      "sector": "상사,자본재",
      "market_cap": 1880407,
      "weight": 2.0,
      "weight_prev": 2.0,
      "today_return": 7.46,
      "contribution": 1.492,
      "cumulative_return": 0.1315803278688632,
      "current_price": 1421000.0,
      "ath_price": 1970000.0,
      "dd": -27.86802030456853,
      "rsi": -2.162561663043727,
      "is_today_new": false
    },
    {
      "code": "161890",
      "name": "한국콜마",
      "sector": "화장품,의류,완구",
      "market_cap": 25352,
      "weight": 2.0,
      "weight_prev": 2.0,
      "today_return": 4.38,
      "contribution": 0.876,
      "cumulative_return": -1.4953913808267383,
      "current_price": 107300.0,
      "ath_price": 117800.0,
      "dd": -8.913412563667233,
      "rsi": -0.971737377102877,
      "is_today_new": false
    },
    {
      "code": "004170",
      "name": "신세계",
      "sector": "소매(유통)",
      "market_cap": 59127,
      "weight": 2.0,
      "weight_prev": 2.0,
      "today_return": 3.47,
      "contribution": 0.6940000000000001,
      "cumulative_return": -11.513360655737714,
      "current_price": 626000.0,
      "ath_price": 776000.0,
      "dd": -19.329896907216494,
      "rsi": -9.823763848836087,
      "is_today_new": false
    },
    {
      "code": "226950",
      "name": "올릭스",
      "sector": "건강관리",
      "market_cap": 25241,
      "weight": 2.0,
      "weight_prev": 2.0,
      "today_return": 2.31,
      "contribution": 0.462,
      "cumulative_return": -19.02633290816327,
      "current_price": 124100.0,
      "ath_price": 207000.0,
      "dd": -40.048309178743956,
      "rsi": -12.464338929221308,
      "is_today_new": false
    },
    {
      "code": "298380",
      "name": "에이비엘바이오",
      "sector": "건강관리",
      "market_cap": 46134,
      "weight": 2.0,
      "weight_prev": 2.0,
      "today_return": 2.36,
      "contribution": 0.472,
      "cumulative_return": -13.363340206185558,
      "current_price": 82100.0,
      "ath_price": 245500.0,
      "dd": -66.55804480651732,
      "rsi": -6.970571834754658,
      "is_today_new": false
    },
    {
      "code": "141080",
      "name": "리가켐바이오",
      "sector": "건강관리",
      "market_cap": 44942,
      "weight": 2.0,
      "weight_prev": 2.0,
      "today_return": 2.71,
      "contribution": 0.5419999999999999,
      "cumulative_return": -12.815094471658506,
      "current_price": 121300.0,
      "ath_price": 213500.0,
      "dd": -43.18501170960187,
      "rsi": -6.725212452878493,
      "is_today_new": false
    }
  ],
  "한투 성과모집형 1차": [
    {
      "code": "005930",
      "name": "삼성전자",
      "sector": "반도체",
      "market_cap": 17246522,
      "weight": 30.0,
      "weight_prev": 20.0,
      "today_return": 6.47,
      "contribution": 12.94,
      "cumulative_return": 10.85405882352941,
      "current_price": 295000.0,
      "ath_price": 362500.0,
      "dd": -18.620689655172416,
      "rsi": 5.683685808127126,
      "is_today_new": false
    },
    {
      "code": "000660",
      "name": "SK하이닉스",
      "sector": "반도체",
      "market_cap": 16107073,
      "weight": 30.0,
      "weight_prev": 20.0,
      "today_return": 3.43,
      "contribution": 6.860000000000001,
      "cumulative_return": 9.146505854800946,
      "current_price": 2253000.0,
      "ath_price": 2919000.0,
      "dd": -22.816032887975336,
      "rsi": 7.903391062514453,
      "is_today_new": false
    },
    {
      "code": "105560",
      "name": "KB금융",
      "sector": "은행",
      "market_cap": 661847,
      "weight": 7.0,
      "weight_prev": 7.0,
      "today_return": 8.81,
      "contribution": 6.167000000000002,
      "cumulative_return": 18.800157894736856,
      "current_price": 186700.0,
      "ath_price": 186700.0,
      "dd": 0.0,
      "rsi": 8.55866605152842,
      "is_today_new": false
    }
  ]
}