{
  "삼성 트루밸류 / NH Value ESG / DB 개방형": [
    {
      "code": "005930",
      "name": "삼성전자",
      "sector": "반도체",
      "market_cap": 11063803.0,
      "weight": 30,
      "today_return": -1.631578947368421,
      "contribution": -4.894736842105264,
      "cumulative_return": 195.10526315789477,
      "is_today_new": false
    },
    {
      "code": "000660",
      "name": "SK하이닉스",
      "sector": "반도체",
      "market_cap": 6638823.0,
      "weight": 15,
      "today_return": -2.4607329842931938,
      "contribution": -3.69109947643979,
      "cumulative_return": 195.5439790575916,
      "is_today_new": false
    },
    {
      "code": "352820",
      "name": "하이브",
      "sector": "미디어,교육",
      "market_cap": 153322.0,
      "weight": 8,
      "today_return": 0.7072135785007072,
      "contribution": 0.5657708628005658,
      "cumulative_return": 71.20226308345119,
      "is_today_new": false
    },
    {
      "code": "001040",
      "name": "CJ",
      "sector": "상사,자본재",
      "market_cap": 52373.0,
      "weight": 8,
      "today_return": -1.643835616438356,
      "contribution": -1.3150684931506849,
      "cumulative_return": 84.90958904109587,
      "is_today_new": false
    },
    {
      "code": "277810",
      "name": "레인보우로보틱스",
      "sector": "기계",
      "market_cap": 146081.0,
      "weight": 8,
      "today_return": 0.6684491978609626,
      "contribution": 0.5347593582887701,
      "cumulative_return": 11.615144726309978,
      "is_today_new": false
    },
    {
      "code": "034020",
      "name": "두산에너빌리티",
      "sector": "기계",
      "market_cap": 656575.0,
      "weight": 5,
      "today_return": 1.4851485148514851,
      "contribution": 0.7425742574257426,
      "cumulative_return": 44.1089108910891,
      "is_today_new": false
    },
    {
      "code": "000150",
      "name": "두산",
      "sector": "상사,자본재",
      "market_cap": 182019.0,
      "weight": 5,
      "today_return": 2.0890099909173476,
      "contribution": 1.0445049954586738,
      "cumulative_return": 3.109900090826523,
      "is_today_new": false
    },
    {
      "code": "006800",
      "name": "미래에셋증권",
      "sector": "증권",
      "market_cap": 395259.0,
      "weight": 3,
      "today_return": -2.380952380952381,
      "contribution": -0.7142857142857142,
      "cumulative_return": 144.04761904761904,
      "is_today_new": false
    },
    {
      "code": "010060",
      "name": "OCI홀딩스",
      "sector": "화학",
      "market_cap": 30694.0,
      "weight": 3,
      "today_return": 12.065439672801636,
      "contribution": 3.619631901840491,
      "cumulative_return": 73.70143149284252,
      "is_today_new": false
    },
    {
      "code": "006400",
      "name": "삼성SDI",
      "sector": "IT가전",
      "market_cap": 320327.0,
      "weight": 3,
      "today_return": -0.625,
      "contribution": -0.1875,
      "cumulative_return": 1.7568390547124446,
      "is_today_new": false
    },
    {
      "code": "241560",
      "name": "두산밥캣",
      "sector": "기계",
      "market_cap": 58185.0,
      "weight": 3,
      "today_return": -0.3284072249589491,
      "contribution": -0.09852216748768472,
      "cumulative_return": -5.208528296984072,
      "is_today_new": false
    },
    {
      "code": "112610",
      "name": "씨에스윈드",
      "sector": "에너지",
      "market_cap": 23279.0,
      "weight": 3,
      "today_return": 6.769825918762089,
      "contribution": 2.0309477756286265,
      "cumulative_return": 11.72880361546289,
      "is_today_new": false
    },
    {
      "code": "439260",
      "name": "대한조선",
      "sector": "기타",
      "market_cap": 39066.0,
      "weight": 3,
      "today_return": 1.9095477386934674,
      "contribution": 0.5728643216080402,
      "cumulative_return": 3.8555592030504293,
      "is_today_new": false
    }
  ]
}